Workbook

Sheet FILTERING OUT TOPICS
A1: Topic ID | B1: Topic ID no url | D1: Topic name | E1: Concat 2 | F1: OA field | G1: OA domain | H1: Code | I1: Claude categorisation | J1: Should we keep this OA topic? | K1: Claude Recommendation | L1: Number of articles (OpenAlex GBQ) | M1: Number of CORDIS projects | N1: Peak score | O1: Top-Q count | P1: Average frontierness | Q1: Frontier 2004-2007 | R1: Frontier 2008-2011 | S1: Frontier 2012-2015 | T1: Frontier 2016-2019 | U1: Frontier 2020-2023 | V1: Frontier 2024-2025 | W1: Best period
A2: https://openalex.org/T13703 | B2: =RIGHT(A2, LEN(A2) - FIND("/T", A2)) -> T13703 | C2: =CONCAT(B2, ",") -> T13703, | D2: Attention Economy in Education and Business | E2: =CONCATENATE(B2," ",D2,",") -> T13703 Attention Economy in Education and Business, | F2: Business, Management and Accounting | G2: Social Sciences | H2: E | I2: Education & pedagogy | J2: Filter out | K2: Filter | L2: 907 | M2: =VLOOKUP(A2,'Matching with Cordis'!A$2:D$3447, 4, FALSE) -> 117 | N2: 0.675 | O2: 2 | P2: =AVERAGE(Q2:V2) -> -0.3155 | Q2: 0.392 | R2: -0.592 | S2: -0.338 | T2: 0.675 | U2: -1.653 | V2: -0.377 | W2: 2016-2019
A3: https://openalex.org/T13436 | B3: =RIGHT(A3, LEN(A3) - FIND("/T", A3)) -> T13436 | C3: =CONCAT(B3, ",") -> T13436, | D3: Space Technology and Applications | E3: =CONCATENATE(B3," ",D3,",") -> T13436 Space Technology and Applications, | F3: Engineering | G3: Physical Sciences | H3: S | I3: Core S&T | J3: Filter out | K3: Keep | L3: 1254 | M3: =VLOOKUP(A3,'Matching with Cordis'!A$2:D$3447, 4, FALSE) -> 74 | N3: 1.156 | O3: 4 | P3: =AVERAGE(Q3:V3) -> 0.2865 | Q3: 0.317 | R3: 0.354 | S3: 1.004 | T3: -0.692 | U3: -0.42 | V3: 1.156 | W3: 2024-2025
A4: https://openalex.org/T13656 | B4: =RIGHT(A4, LEN(A4) - FIND("/T", A4)) -> T13656 | C4: =CONCAT(B4, ",") -> T13656, | D4: Science, Research, and Medicine | E4: =CONCATENATE(B4," ",D4,",") -> T13656 Science, Research, and Medicine, | F4: Medicine | G4: Health Sciences | H4: X | I4: Catch-all / vague | J4: Filter out | K4: Filter | L4: 44911 | M4: =VLOOKUP(A4,'Matching with Cordis'!A$2:D$3447, 4, FALSE) -> 74 | N4: 0.512 | O4: 1 | P4: =AVERAGE(Q4:V4) -> -0.19933333 | Q4: -0.57 | R4: -0.392 | S4: -0.17 | T4: -0.429 | U4: -0.147 | V4: 0.512 | W4: 2024-2025
A5: https://openalex.org/T10289 | B5: =RIGHT(A5, LEN(A5) - FIND("/T", A5)) -> T10289 | C5: =CONCAT(B5, ",") -> T10289, | D5: European Union Policy and Governance | E5: =CONCATENATE(B5," ",D5,",") -> T10289 European Union Policy and Governance, | F5: Social Sciences | G5: Social Sciences | H5: P | I5: Social science & policy | J5: Filter out | K5: Review | L5: 86922 | M5: =VLOOKUP(A5,'Matching with Cordis'!A$2:D$3447, 4, FALSE) -> 72 | N5: -0.196 | O5: 0 | P5: =AVERAGE(Q5:V5) -> -0.44966667 | Q5: -0.196 | R5: -0.485 | S5: -0.433 | T5: -0.44 | U5: -0.773 | V5: -0.371 | W5: 2004-2007
A6: https://openalex.org/T14152 | B6: =RIGHT(A6, LEN(A6) - FIND("/T", A6)) -> T14152 | C6: =CONCAT(B6, ",") -> T14152, | D6: Healthcare Facilities Design and Sustainability | E6: =CONCATENATE(B6," ",D6,",") -> T14152 Healthcare Facilities Design and Sustainability, | F6: Social Sciences | G6: Social Sciences | H6: P | I6: Social science & policy | J6: Filter out | K6: Review | L6: 1893 | M6: =VLOOKUP(A6,'Matching with Cordis'!A$2:D$3447, 4, FALSE) -> 66 | N6: 1.389 | O6: 6 | P6: =AVERAGE(Q6:V6) -> 0.97016667 | Q6: 1.389 | R6: 0.885 | S6: 0.963 | T6: 0.809 | U6: 1.089 | V6: 0.686 | W6: 2004-2007
A7: https://openalex.org/T14347 | B7: =RIGHT(A7, LEN(A7) - FIND("/T", A7)) -> T14347 | C7: =CONCAT(B7, ",") -> T14347, | D7: Big Data and Digital Economy | E7: =CONCATENATE(B7," ",D7,",") -> T14347 Big Data and Digital Economy, | F7: Computer Science | G7: Physical Sciences | H7: S | I7: Core S&T | J7: Filter out | K7: Keep | L7: 1572 | M7: =VLOOKUP(A7,'Matching with Cordis'!A$2:D$3447, 4, FALSE) -> 59 | N7: 4.479 | O7: 6 | P7: =AVERAGE(Q7:V7) -> 2.4516667 | Q7: 4.479 | R7: 0.694 | S7: 3.634 | T7: 2.471 | U7: 1.661 | V7: 1.771 | W7: 2004-2007
A8: https://openalex.org/T14440 | B8: =RIGHT(A8, LEN(A8) - FIND("/T", A8)) -> T14440 | C8: =CONCAT(B8, ",") -> T14440, | D8: Quality of Life Measurement | E8: =CONCATENATE(B8," ",D8,",") -> T14440 Quality of Life Measurement, | F8: Social Sciences | G8: Social Sciences | H8: P | I8: Social science & policy | J8: Filter out | K8: Review | L8: 1711 | M8: =VLOOKUP(A8,'Matching with Cordis'!A$2:D$3447, 4, FALSE) -> 53 | N8: 1.745 | O8: 5 | P8: =AVERAGE(Q8:V8) -> 0.8545 | Q8: 0.231 | R8: 1.334 | S8: 1.745 | T8: 0.978 | U8: 0.454 | V8: 0.385 | W8: 2012-2015
A9: https://openalex.org/T12981 | B9: =RIGHT(A9, LEN(A9) - FIND("/T", A9)) -> T12981 | C9: =CONCAT(B9, ",") -> T12981, | D9: Conservation Techniques and Studies | E9: =CONCATENATE(B9," ",D9,",") -> T12981 Conservation Techniques and Studies, | F9: Arts and Humanities | G9: Social Sciences | H9: H | I9: Humanities & culture | J9: Filter out | K9: Filter | L9: 17772 | M9: =VLOOKUP(A9,'Matching with Cordis'!A$2:D$3447, 4, FALSE) -> 51 | N9: 0.377 | O9: 3 | P9: =AVERAGE(Q9:V9) -> 0.20516667 | Q9: -0.037 | R9: 0.179 | S9: 0.377 | T9: 0.32 | U9: 0.313 | V9: 0.079 | W9: 2012-2015
A10: https://openalex.org/T14213 | B10: =RIGHT(A10, LEN(A10) - FIND("/T", A10)) -> T14213 | C10: =CONCAT(B10, ",") -> T14213, | D10: Global Politics and Economy | E10: =CONCATENATE(B10," ",D10,",") -> T14213 Global Politics and Economy, | F10: Economics, Econometrics and Finance | G10: Social Sciences | H10: P | I10: Social science & policy | J10: Filter out | K10: Review | L10: 5771 | M10: =VLOOKUP(A10,'Matching with Cordis'!A$2:D$3447, 4, FALSE) -> 51 | N10: 0.179 | O10: 0 | P10: =AVERAGE(Q10:V10) -> -0.27666667 | Q10: -0.828 | R10: 0.179 | S10: -0.083 | T10: -0.591 | U10: -0.482 | V10: 0.145 | W10: 2008-2011
A11: https://openalex.org/T12959 | B11: =RIGHT(A11, LEN(A11) - FIND("/T", A11)) -> T12959 | C11: =CONCAT(B11, ",") -> T12959, | D11: Engineering and Materials Science Studies | E11: =CONCATENATE(B11," ",D11,",") -> T12959 Engineering and Materials Science Studies, | F11: Engineering | G11: Physical Sciences | H11: S | I11: Core S&T | J11: Filter out | K11: Keep | L11: 34569 | M11: =VLOOKUP(A11,'Matching with Cordis'!A$2:D$3447, 4, FALSE) -> 51 | N11: 0.005 | O11: 0 | P11: =AVERAGE(Q11:V11) -> -0.29716667 | Q11: -0.491 | R11: -0.531 | S11: -0.14 | T11: -0.34 | U11: -0.286 | V11: 0.005 | W11: 2024-2025
A12: https://openalex.org/T14491 | B12: =RIGHT(A12, LEN(A12) - FIND("/T", A12)) -> T14491 | C12: =CONCAT(B12, ",") -> T14491, | D12: Diverse academic and cultural studies | E12: =CONCATENATE(B12," ",D12,",") -> T14491 Diverse academic and cultural studies, | F12: Economics, Econometrics and Finance | G12: Social Sciences | H12: X | I12: Catch-all / vague | J12: Filter out | K12: Filter | L12: 85811 | M12: =VLOOKUP(A12,'Matching with Cordis'!A$2:D$3447, 4, FALSE) -> 49 | N12: 0.015 | O12: 0 | P12: =AVERAGE(Q12:V12) -> -0.43 | Q12: 0.015 | R12: -0.13 | S12: -0.445 | T12: -0.341 | U12: -1.007 | V12: -0.672 | W12: 2004-2007
A13: https://openalex.org/T10731 | B13: =RIGHT(A13, LEN(A13) - FIND("/T", A13)) -> T10731 | C13: =CONCAT(B13, ",") -> T10731, | D13: Educational Games and Gamification | E13: =CONCATENATE(B13," ",D13,",") -> T10731 Educational Games and Gamification, | F13: Psychology | G13: Social Sciences | H13: E | I13: Education & pedagogy | J13: Filter out | K13: Filter | L13: 58782 | M13: =VLOOKUP(A13,'Matching with Cordis'!A$2:D$3447, 4, FALSE) -> 41 | N13: 1.163 | O13: 6 | P13: =AVERAGE(Q13:V13) -> 0.81716667 | Q13: 1.163 | R13: 1.093 | S13: 0.838 | T13: 0.686 | U13: 0.443 | V13: 0.68 | W13: 2004-2007
... A20: https://openalex.org/T12686 | B20: =RIGHT(A20, LEN(A20) - FIND("/T", A20)) -> T12686 | C20: =CONCAT(B20, ",") -> T12686, | D20: Central European national history | E20: =CONCATENATE(B20," ",D20,",") -> T12686 Central European national history, | F20: Social Sciences | G20: Social Sciences | H20: K | I20: Country/region-specific | J20: Filter out | K20: Filter | L20: 2982 | M20: =VLOOKUP(A20,'Matching with Cordis'!A$2:D$3447, 4, FALSE) -> 22 | N20: -0.199 | O20: 0 | P20: =AVERAGE(Q20:V20) -> -0.3285 | Q20: -0.725 | R20: -0.273 | S20: -0.24 | T20: -0.281 | U20: -0.253 | V20: -0.199 | W20: 2024-2025
A21: https://openalex.org/T13146 | B21: =RIGHT(A21, LEN(A21) - FIND("/T", A21)) -> T13146 | D21: Sustainable Finance and Green Bonds | F21: Economics, Econometrics and Finance | G21: Social Sciences | H21: T | I21: Applied S&T | J21: Keep | K21: Keep | L21: 7159 | M21: =VLOOKUP(A21,'Matching with Cordis'!A$2:D$3447, 4, FALSE) -> 21 | N21: 3.177 | O21: 6 | P21: =AVERAGE(Q21:V21) -> 2.4296667 | Q21: 3.177 | R21: 1.849 | S21: 1.736 | T21: 2.678 | U21: 3.007 | V21: 2.131 | W21: 2004-2007
A22: https://openalex.org/T14296 | B22: =RIGHT(A22, LEN(A22) - FIND("/T", A22)) -> T14296 | C22: =CONCAT(B22, ",") -> T14296, | D22: Climate Change and Sustainable Development | E22: =CONCATENATE(B22," ",D22,",") -> T14296 Climate Change and Sustainable Development, | F22: Environmental Science | G22: Physical Sciences | H22: S | I22: Core S&T | J22: Filter out | K22: Keep | L22: 2824 | M22: =VLOOKUP(A22,'Matching with Cordis'!A$2:D$3447, 4, FALSE) -> 21 | N22: 1.839 | O22: 3 | P22: =AVERAGE(Q22:V22) -> 0.40433333 | Q22: -0.066 | R22: 1.839 | S22: 0.868 | T22: -0.622 | U22: 0.071 | V22: 0.336 | W22: 2008-2011
A23: https://openalex.org/T11714 | B23: =RIGHT(A23, LEN(A23) - FIND("/T", A23)) -> T11714 | D23: Multimodal Machine Learning Applications | F23: Computer Science | G23: Physical Sciences | H23: S | I23: Core S&T | J23: Keep | K23: Keep | L23: 17242 | M23: =VLOOKUP(A23,'Matching with Cordis'!A$2:D$3447, 4, FALSE) -> 17 | N23: 3.737 | O23: 6 | P23: =AVERAGE(Q23:V23) -> 2.4191667 | Q23: 2.52 | R23: 3.737 | S23: 2.703 | T23: 3.188 | U23: 1.984 | V23: 0.383 | W23: 2008-2011
A24: https://openalex.org/T11776 | B24: =RIGHT(A24, LEN(A24) - FIND("/T", A24)) -> T11776 | C24: =CONCAT(B24, ",") -> T11776, | D24: Irish and British Studies | E24: =CONCATENATE(B24," ",D24,",") -> T11776 Irish and British Studies, | F24: Social Sciences | G24: Social Sciences | H24: K | I24: Country/region-specific | J24: Filter out | K24: Filter | L24: 62929 | M24: =VLOOKUP(A24,'Matching with Cordis'!A$2:D$3447, 4, FALSE) -> 20 | N24: -0.522 | O24: 0 | P24: =AVERAGE(Q24:V24) -> -0.67466667 | Q24: -0.522 | R24: -0.861 | S24: -0.592 | T24: -0.622 | U24: -0.872 | V24: -0.579 | W24: 2004-2007
A25: https://openalex.org/T11765 | B25: =RIGHT(A25, LEN(A25) - FIND("/T", A25)) -> T11765 | D25: Circular RNAs in diseases | F25: Biochemistry, Genetics and Molecular Biology | G25: Life Sciences | H25: B | I25: Biomedical research | J25: Keep | K25: Keep | L25: 20510 | M25: =VLOOKUP(A25,'Matching with Cordis'!A$2:D$3447, 4, FALSE) -> 3 | N25: 4.987 | O25: 5 | P25: =AVERAGE(Q25:V25) -> 2.3778333 | Q25: 4.987 | R25: 3.796 | S25: 2.279 | T25: 1.789 | U25: 1.174 | V25: 0.242 | W25: 2004-2007
A26: https://openalex.org/T13298 | B26: =RIGHT(A26, LEN(A26) - FIND("/T", A26)) -> T13298 | C26: =CONCAT(B26, ",") -> T13298, | D26: Solar Energy Systems and Technologies | E26: =CONCATENATE(B26," ",D26,",") -> T13298 Solar Energy Systems and Technologies, | F26: Engineering | G26: Physical Sciences | H26: S | I26: Core S&T | J26: Filter out | K26: Keep | L26: 5038 | M26: =VLOOKUP(A26,'Matching with Cordis'!A$2:D$3447, 4, FALSE) -> 16 | N26: 1.364 | O26: 6 | P26: =AVERAGE(Q26:V26) -> 0.9905 | Q26: 1.102 | R26: 1.279 | S26: 1.364 | T26: 0.915 | U26: 0.769 | V26: 0.514 | W26: 2012-2015
A27: https://openalex.org/T13754 | B27: =RIGHT(A27, LEN(A27) - FIND("/T", A27)) -> T13754 | C27: =CONCAT(B27, ",") -> T13754, | D27: Central European and Russian historical studies | E27: =CONCATENATE(B27," ",D27,",") -> T13754 Central European and Russian historical studies, | F27: Social Sciences | G27: Social Sciences | H27: K | I27: Country/region-specific | J27: Filter out | K27: Filter | L27: 8777 | M27: =VLOOKUP(A27,'Matching with Cordis'!A$2:D$3447, 4, FALSE) -> 16 | N27: 1.016 | O27: 4 | P27: =AVERAGE(Q27:V27) -> 0.52616667 | Q27: -0.154 | R27: 0.471 | S27: 0.909 | T27: 0.637 | U27: 1.016 | V27: 0.278 | W27: 2020-2023
A28: https://openalex.org/T14185 | B28: =RIGHT(A28, LEN(A28) - FIND("/T", A28)) -> T14185 | C28: =CONCAT(B28, ",") -> T14185, | D28: Research, Science, and Academia | E28: =CONCATENATE(B28," ",D28,",") -> T14185 Research, Science, and Academia, | F28: Decision Sciences | G28: Social Sciences | H28: X | I28: Catch-all / vague | J28: Filter out | K28: Filter | L28: 15270 | M28: =VLOOKUP(A28,'Matching with Cordis'!A$2:D$3447, 4, FALSE) -> 16 | N28: 0.496 | O28: 1 | P28: =AVERAGE(Q28:V28) -> -0.513 | Q28: 0.136 | R28: -0.551 | S28: -1.171 | T28: -1.26 | U28: -0.728 | V28: 0.496 | W28: 2024-2025
A29: https://openalex.org/T14411 | B29: =RIGHT(A29, LEN(A29) - FIND("/T", A29)) -> T14411 | C29: =CONCAT(B29, ",") -> T14411, | D29: Undergraduate Neuroscience Education and Research | E29: =CONCATENATE(B29," ",D29,",") -> T14411 Undergraduate Neuroscience Education and Research, | F29: Neuroscience | G29: Life Sciences | H29: E | I29: Education & pedagogy | J29: Filter out | K29: Filter | L29: 479 | M29: =VLOOKUP(A29,'Matching with Cordis'!A$2:D$3447, 4, FALSE) -> 15 | N29: 1.607 | O29: 5 | P29: =AVERAGE(Q29:V29) -> 0.75833333 | Q29: 0.783 | R29: 1.607 | S29: 0.451 | T29: 0.625 | U29: 0.099 | V29: 0.985 | W29: 2008-2011
A30: https://openalex.org/T11636 | B30: =RIGHT(A30, LEN(A30) - FIND("/T", A30)) -> T11636 | D30: Artificial Intelligence in Healthcare and Education | F30: Medicine | G30: Health Sciences | H30: T | I30: Applied S&T | J30: Keep | K30: Keep | L30: 33454 | M30: =VLOOKUP(A30,'Matching with Cordis'!A$2:D$3447, 4, FALSE) -> 35 | N30: 3.664 | O30: 6 | P30: =AVERAGE(Q30:V30) -> 2.2396667 | Q30: 1.156 | R30: 0.91 | S30: 1.387 | T30: 3.664 | U30: 3.454 | V30: 2.867 | W30: 2016-2019
A31: https://openalex.org/T11458 | B31: =RIGHT(A31, LEN(A31) - FIND("/T", A31)) -> T11458 | D31: Advanced Wireless Communication Technologies | F31: Engineering | G31: Physical Sciences | H31: S | I31: Core S&T | J31: Keep | K31: Keep | L31: 21681 | M31: =VLOOKUP(A31,'Matching with Cordis'!A$2:D$3447, 4, FALSE) -> 39 | N31: 5.426 | O31: 5 | P31: =AVERAGE(Q31:V31) -> 2.2265 | Q31: 5.426 | R31: 2.578 | S31: 1.468 | T31: 2.06 | U31: 1.773 | V31: 0.054 | W31: 2004-2007
A32: https://openalex.org/T11342 | B32: =RIGHT(A32, LEN(A32) - FIND("/T", A32)) -> T11342 | D32: Carbon and Quantum Dots Applications | F32: Materials Science | G32: Physical Sciences | H32: S | I32: Core S&T | J32: Keep | K32: Keep | L32: 23715 | M32: =VLOOKUP(A32,'Matching with Cordis'!A$2:D$3447, 4, FALSE) -> 13 | N32: 3.443 | O32: 6 | P32: =AVERAGE(Q32:V32) -> 2.2261667 | Q32: 2.395 | R32: 3.443 | S32: 3.26 | T32: 1.957 | U32: 1.304 | V32: 0.998 | W32: 2008-2011
A33: https://openalex.org/T14292 | B33: =RIGHT(A33, LEN(A33) - FIND("/T", A33)) -> T14292 | C33: =CONCAT(B33, ",") -> T14292, | D33: Migration, Policy, and Dickens Studies | E33: =CONCATENATE(B33," ",D33,",") -> T14292 Migration, Policy, and Dickens Studies, | F33: Social Sciences | G33: Social Sciences | H33: P | I33: Social science & policy | J33: Filter out | K33: Review | L33: 9689 | M33: =VLOOKUP(A33,'Matching with Cordis'!A$2:D$3447, 4, FALSE) -> 15 | N33: 0.136 | O33: 0 | P33: =AVERAGE(Q33:V33) -> -0.38983333 | Q33: -0.535 | R33: -0.071 | S33: -0.322 | T33: -0.807 | U33: -0.74 | V33: 0.136 | W33: 2024-2025
A34: https://openalex.org/T10036 | B34: =RIGHT(A34, LEN(A34) - FIND("/T", A34)) -> T10036 | D34: Advanced Neural Network Applications | F34: Computer Science | G34: Physical Sciences | H34: S | I34: Core S&T | J34: Keep | K34: Keep | L34: 48260 | M34: =VLOOKUP(A34,'Matching with Cordis'!A$2:D$3447, 4, FALSE) -> 13 | N34: 3.459 | O34: 6 | P34: =AVERAGE(Q34:V34) -> 2.1771667 | Q34: 2.607 | R34: 1.457 | S34: 3.459 | T34: 3.168 | U34: 1.896 | V34: 0.476 | W34: 2012-2015
A35: https://openalex.org/T12026 | B35: =RIGHT(A35, LEN(A35) - FIND("/T", A35)) -> T12026 | D35: Explainable Artificial Intelligence (XAI) | F35: Computer Science | G35: Physical Sciences | H35: S | I35: Core S&T | J35: Keep | K35: Keep | L35: 10711 | M35: =VLOOKUP(A35,'Matching with Cordis'!A$2:D$3447, 4, FALSE) -> 36 | N35: 4.041 | O35: 6 | P35: =AVERAGE(Q35:V35) -> 2.1621667 | Q35: 0.595 | R35: 0.753 | S35: 2.962 | T35: 4.041 | U35: 2.927 | V35: 1.695 | W35: 2016-2019
A36: https://openalex.org/T13893 | B36: =RIGHT(A36, LEN(A36) - FIND("/T", A36)) -> T13893 | C36: =CONCAT(B36, ",") -> T13893, | D36: Sustainable Development and Policies | E36: =CONCATENATE(B36," ",D36,",") -> T13893 Sustainable Development and Policies, | F36: Environmental Science | G36: Physical Sciences | H36: S | I36: Core S&T | J36: Filter out | K36: Keep | L36: 751 | M36: =VLOOKUP(A36,'Matching with Cordis'!A$2:D$3447, 4, FALSE) -> 15 | N36: 1.234 | O36: 1 | P36: =AVERAGE(Q36:V36) -> -0.39466667 | Q36: 0.171 | R36: 1.234 | S36: -0.493 | T36: -1.976 | U36: -0.734 | V36: -0.57 | W36: 2008-2011
A37: https://openalex.org/T12432 | B37: =RIGHT(A37, LEN(A37) - FIND("/T", A37)) -> T12432 | C37: =CONCAT(B37, ",") -> T12432, | D37: Arctic and Russian Policy Studies | E37: =CONCATENATE(B37," ",D37,",") -> T12432 Arctic and Russian Policy Studies, | F37: Social Sciences | G37: Social Sciences | H37: K | I37: Country/region-specific | J37: Filter out | K37: Filter | L37: 54598 | M37: =VLOOKUP(A37,'Matching with Cordis'!A$2:D$3447, 4, FALSE) -> 14 | N37: 1.243 | O37: 5 | P37: =AVERAGE(Q37:V37) -> 0.73366667 | Q37: 0.453 | R37: 1.243 | S37: 0.86 | T37: 0.952 | U37: 0.796 | V37: 0.098 | W37: 2008-2011
A38: https://openalex.org/T12627 | B38: =RIGHT(A38, LEN(A38) - FIND("/T", A38)) -> T12627 | D38: Graphene and Nanomaterials Applications | F38: Engineering | G38: Physical Sciences | H38: S | I38: Core S&T | J38: Keep | K38: Keep | L38: 26001 | M38: =VLOOKUP(A38,'Matching with Cordis'!A$2:D$3447, 4, FALSE) -> 28 | N38: 3.966 | O38: 6 | P38: =AVERAGE(Q38:V38) -> 2.1271667 | Q38: 3.217 | R38: 3.966 | S38: 2.2 | T38: 1.385 | U38: 1.065 | V38: 0.93 | W38: 2008-2011
A39: https://openalex.org/T10628 | B39: =RIGHT(A39, LEN(A39) - FIND("/T", A39)) -> T10628 | C39: =CONCAT(B39, ",") -> T10628, | D39: China's Socioeconomic Reforms and Governance | E39: =CONCATENATE(B39," ",D39,",") -> T10628 China's Socioeconomic Reforms and Governance, | F39: Social Sciences | G39: Social Sciences | H39: K | I39: Country/region-specific | J39: Filter out | K39: Filter | L39: 42548 | M39: =VLOOKUP(A39,'Matching with Cordis'!A$2:D$3447, 4, FALSE) -> 14 | N39: -0.018 | O39: 0 | P39: =AVERAGE(Q39:V39) -> -0.069333333 | Q39: -0.03 | R39: -0.062 | S39: -0.194 | T39: -0.018 | U39: -0.018 | V39: -0.094 | W39: 2020-2023
A40: https://openalex.org/T12337 | B40: =RIGHT(A40, LEN(A40) - FIND("/T", A40)) -> T12337 | C40: =CONCAT(B40, ",") -> T12337, | D40: Italian Fascism and Post-war Society | E40: =CONCATENATE(B40," ",D40,",") -> T12337 Italian Fascism and Post-war Society, | F40: Social Sciences | G40: Social Sciences | H40: K | I40: Country/region-specific | J40: Filter out | K40: Filter | L40: 100026 | M40: =VLOOKUP(A40,'Matching with Cordis'!A$2:D$3447, 4, FALSE) -> 14 | N40: 0.092 | O40: 0 | P40: =AVERAGE(Q40:V40) -> -0.31233333 | Q40: -0.399 | R40: -0.402 | S40: -0.362 | T40: -0.134 | U40: -0.669 | V40: 0.092 | W40: 2024-2025
A41: https://openalex.org/T12312 | B41: =RIGHT(A41, LEN(A41) - FIND("/T", A41)) -> T12312 | C41: =CONCAT(B41, ",") -> T12312, | D41: Culture, Economy, and Development Studies | E41: =CONCATENATE(B41," ",D41,",") -> T12312 Culture, Economy, and Development Studies, | F41: Social Sciences | G41: Social Sciences | H41: P | I41: Social science & policy | J41: Filter out | K41: Review | L41: 12287 | M41: =VLOOKUP(A41,'Matching with Cordis'!A$2:D$3447, 4, FALSE) -> 14 | N41: 0.128 | O41: 0 | P41: =AVERAGE(Q41:V41) -> -0.4325 | Q41: 0.128 | R41: 0.024 | S41: -0.513 | T41: -0.621 | U41: -0.752 | V41: -0.861 | W41: 2004-2007
A42: https://openalex.org/T11198 | B42: =RIGHT(A42, LEN(A42) - FIND("/T", A42)) -> T11198 | C42: =CONCAT(B42, ",") -> T11198, | D42: Japanese History and Culture | E42: =CONCATENATE(B42," ",D42,",") -> T11198 Japanese History and Culture, | F42: Social Sciences | G42: Social Sciences | H42: K | I42: Country/region-specific | J42: Filter out | K42: Filter | L42: 88913 | M42: =VLOOKUP(A42,'Matching with Cordis'!A$2:D$3447, 4, FALSE) -> 14 | N42: -0.034 | O42: 0 | P42: =AVERAGE(Q42:V42) -> -0.44716667 | Q42: -0.694 | R42: -0.386 | S42: -0.498 | T42: -0.523 | U42: -0.548 | V42: -0.034 | W42: 2024-2025
A43: https://openalex.org/T14242 | B43: =RIGHT(A43, LEN(A43) - FIND("/T", A43)) -> T14242 | C43: =CONCAT(B43, ",") -> T14242, | D43: Nutrition, Health, and Society Studies | E43: =CONCATENATE(B43," ",D43,",") -> T14242 Nutrition, Health, and Society Studies, | F43: Agricultural and Biological Sciences | G43: Life Sciences | H43: T | I43: Applied S&T | J43: Filter out | K43: Keep | L43: 2767 | M43: =VLOOKUP(A43,'Matching with Cordis'!A$2:D$3447, 4, FALSE) -> 14 | N43: 0.995 | O43: 1 | P43: =AVERAGE(Q43:V43) -> -0.71683333 | Q43: -0.528 | R43: 0.995 | S43: -2.044 | T43: -0.783 | U43: -1.423 | V43: -0.518 | W43: 2008-2011
A44: https://openalex.org/T11133 | B44: =RIGHT(A44, LEN(A44) - FIND("/T", A44)) -> T11133 | D44: UAV Applications and Optimization | F44: Engineering | G44: Physical Sciences | H44: S | I44: Core S&T | J44: Keep | K44: Keep | L44: 20055 | M44: =VLOOKUP(A44,'Matching with Cordis'!A$2:D$3447, 4, FALSE) -> 81 | N44: 3.023 | O44: 6 | P44: =AVERAGE(Q44:V44) -> 2.048 | Q44: 3.023 | R44: 1.324 | S44: 2.054 | T44: 3.021 | U44: 2.137 | V44: 0.729 | W44: 2004-2007
A45: https://openalex.org/T13819 | B45: =RIGHT(A45, LEN(A45) - FIND("/T", A45)) -> T13819 | C45: =CONCAT(B45, ",") -> T13819, | D45: Collaborative and Sustainable Housing Initiatives | E45: =CONCATENATE(B45," ",D45,",") -> T13819 Collaborative and Sustainable Housing Initiatives, | F45: Social Sciences | G45: Social Sciences | H45: P | I45: Social science & policy | J45: Filter out | K45: Review | L45: 2241 | M45: =VLOOKUP(A45,'Matching with Cordis'!A$2:D$3447, 4, FALSE) -> 13 | N45: 1.139 | O45: 5 | P45: =AVERAGE(Q45:V45) -> 0.71716667 | Q45: 1.122 | R45: 0.882 | S45: 1.139 | T45: 0.62 | U45: 0.275 | V45: 0.265 | W45: 2012-2015
A46: https://openalex.org/T13894 | B46: =RIGHT(A46, LEN(A46) - FIND("/T", A46)) -> T13894 | C46: =CONCAT(B46, ",") -> T13894, | D46: Indian Economic and Social Development | E46: =CONCATENATE(B46," ",D46,",") -> T13894 Indian Economic and Social Development, | F46: Economics, Econometrics and Finance | G46: Social Sciences | H46: K | I46: Country/region-specific | J46: Filter out | K46: Filter | L46: 29668 | M46: =VLOOKUP(A46,'Matching with Cordis'!A$2:D$3447, 4, FALSE) -> 13 | N46: 0.35 | O46: 2 | P46: =AVERAGE(Q46:V46) -> 0.0585 | Q46: 0.35 | R46: -0.223 | S46: 0.046 | T46: -0.261 | U46: 0.09 | V46: 0.349 | W46: 2004-2007
A47: https://openalex.org/T13302 | B47: =RIGHT(A47, LEN(A47) - FIND("/T", A47)) -> T13302 | C47: =CONCAT(B47, ",") -> T13302, | D47: Amazonian Archaeology and Ethnohistory | E47: =CONCATENATE(B47," ",D47,",") -> T13302 Amazonian Archaeology and Ethnohistory, | F47: Arts and Humanities | G47: Social Sciences | H47: K | I47: Country/region-specific | J47: Filter out | K47: Filter | L47: 6460 | M47: =VLOOKUP(A47,'Matching with Cordis'!A$2:D$3447, 4, FALSE) -> 13 | N47: -0.21 | O47: 0 | P47: =AVERAGE(Q47:V47) -> -0.53416667 | Q47: -0.956 | R47: -0.439 | S47: -0.601 | T47: -0.386 | U47: -0.613 | V47: -0.21 | W47: 2024-2025
A48: https://openalex.org/T14222 | B48: =RIGHT(A48, LEN(A48) - FIND("/T", A48)) -> T14222 | C48: =CONCAT(B48, ",") -> T14222, | D48: Knowledge Management and Technology | E48: =CONCATENATE(B48," ",D48,",") -> T14222 Knowledge Management and Technology, | F48: Decision Sciences | G48: Social Sciences | H48: M | I48: Business & management | J48: Filter out | K48: Filter | L48: 3608 | M48: =VLOOKUP(A48,'Matching with Cordis'!A$2:D$3447, 4, FALSE) -> 12 | N48: 1.041 | O48: 4 | P48: =AVERAGE(Q48:V48) -> 0.50666667 | Q48: 0.14 | R48: -0.138 | S48: 0.734 | T48: 0.499 | U48: 0.764 | V48: 1.041 | W48: 2024-2025
A49: https://openalex.org/T13778 | B49: =RIGHT(A49, LEN(A49) - FIND("/T", A49)) -> T13778 | C49: =CONCAT(B49, ",") -> T13778, | D49: Comparative and World Literature | E49: =CONCATENATE(B49," ",D49,",") -> T13778 Comparative and World Literature, | F49: Arts and Humanities | G49: Social Sciences | H49: H | I49: Humanities & culture | J49: Filter out | K49: Filter | L49: 1108 | M49: =VLOOKUP(A49,'Matching with Cordis'!A$2:D$3447, 4, FALSE) -> 12 | N49: 1.681 | O49: 1 | P49: =AVERAGE(Q49:V49) -> 0.054333333 | Q49: 1.681 | R49: -0.175 | S49: -0.584 | T49: -0.491 | U49: -0.293 | V49: 0.188 | W49: 2004-2007
A50: https://openalex.org/T12473 | B50: =RIGHT(A50, LEN(A50) - FIND("/T", A50)) -> T12473 | C50: =CONCAT(B50, ",") -> T12473, | D50: Pacific and Southeast Asian Studies | E50: =CONCATENATE(B50," ",D50,",") -> T12473 Pacific and Southeast Asian Studies, | F50: Social Sciences | G50: Social Sciences | H50: K | I50: Country/region-specific | J50: Filter out | K50: Filter | L50: 26026 | M50: =VLOOKUP(A50,'Matching with Cordis'!A$2:D$3447, 4, FALSE) -> 12 | N50: 0.043 | O50: 0 | P50: =AVERAGE(Q50:V50) -> -0.23116667 | Q50: -0.137 | R50: 0.043 | S50: -0.375 | T50: -0.139 | U50: -0.459 | V50: -0.32 | W50: 2008-2011
A51: https://openalex.org/T13995 | B51: =RIGHT(A51, LEN(A51) - FIND("/T", A51)) -> T13995 | C51: =CONCAT(B51, ",") -> T13995, | D51: Globalization and political ideologies | E51: =CONCATENATE(B51," ",D51,",") -> T13995 Globalization and political ideologies, | F51: Social Sciences | G51: Social Sciences | H51: P | I51: Social science & policy | J51: Filter out | K51: Review | L51: 1690 | M51: =VLOOKUP(A51,'Matching with Cordis'!A$2:D$3447, 4, FALSE) -> 12 | N51: 0.276 | O51: 0 | P51: =AVERAGE(Q51:V51) -> -0.24816667 | Q51: -0.417 | R51: -1.069 | S51: -0.007 | T51: 0.167 | U51: -0.439 | V51: 0.276 | W51: 2024-2025
A52: https://openalex.org/T14355 | B52: =RIGHT(A52, LEN(A52) - FIND("/T", A52)) -> T14355 | C52: =CONCAT(B52, ",") -> T14355, | D52: Historical Studies of British Isles | E52: =CONCATENATE(B52," ",D52,",") -> T14355 Historical Studies of British Isles, | F52: Arts and Humanities | G52: Social Sciences | H52: K | I52: Country/region-specific | J52: Filter out | K52: Filter | L52: 22717 | M52: =VLOOKUP(A52,'Matching with Cordis'!A$2:D$3447, 4, FALSE) -> 12 | N52: -0.211 | O52: 0 | P52: =AVERAGE(Q52:V52) -> -0.51633333 | Q52: -0.586 | R52: -0.835 | S52: -0.294 | T52: -0.481 | U52: -0.691 | V52: -0.211 | W52: 2024-2025
A53: https://openalex.org/T12892 | B53: =RIGHT(A53, LEN(A53) - FIND("/T", A53)) -> T12892 | C53: =CONCAT(B53, ",") -> T12892, | D53: Social Power and Status Dynamics | E53: =CONCATENATE(B53," ",D53,",") -> T12892 Social Power and Status Dynamics, | F53: Social Sciences | G53: Social Sciences | H53: P | I53: Social science & policy | J53: Filter out | K53: Review | L53: 1145 | M53: =VLOOKUP(A53,'Matching with Cordis'!A$2:D$3447, 4, FALSE) -> 12 | N53: -1.005 | O53: 0 | P53: =AVERAGE(Q53:V53) -> -1.2461667 | Q53: -1.005 | R53: -1.404 | S53: -1.305 | T53: -1.092 | U53: -1.412 | V53: -1.259 | W53: 2004-2007
A54: https://openalex.org/T13287 | B54: =RIGHT(A54, LEN(A54) - FIND("/T", A54)) -> T13287 | C54: =CONCAT(B54, ",") -> T13287, | D54: Robotic Process Automation Applications | E54: =CONCATENATE(B54," ",D54,",") -> T13287 Robotic Process Automation Applications, | F54: Engineering | G54: Physical Sciences | H54: S | I54: Core S&T | J54: Filter out | K54: Keep | L54: 2388 | M54: =VLOOKUP(A54,'Matching with Cordis'!A$2:D$3447, 4, FALSE) -> 11 | N54: 4.494 | O54: 5 | P54: =AVERAGE(Q54:V54) -> 1.7906667 | Q54: 0.917 | R54: -0.365 | S54: 1.439 | T54: 4.494 | U54: 2.673 | V54: 1.586 | W54: 2016-2019
A55: https://openalex.org/T13812 | B55: =RIGHT(A55, LEN(A55) - FIND("/T", A55)) -> T13812 | C55: =CONCAT(B55, ",") -> T13812, | D55: AI and HR Technologies | E55: =CONCATENATE(B55," ",D55,",") -> T13812 AI and HR Technologies, | F55: Business, Management and Accounting | G55: Social Sciences | H55: T | I55: Applied S&T | J55: Filter out | K55: Keep | L55: 7530 | M55: =VLOOKUP(A55,'Matching with Cordis'!A$2:D$3447, 4, FALSE) -> 11 | N55: 2.084 | O55: 6 | P55: =AVERAGE(Q55:V55) -> 1.4733333 | Q55: 1.69 | R55: 0.388 | S55: 1.158 | T55: 1.553 | U55: 1.967 | V55: 2.084 | W55: 2024-2025
A56: https://openalex.org/T11775 | B56: =RIGHT(A56, LEN(A56) - FIND("/T", A56)) -> T11775 | D56: COVID-19 diagnosis using AI | F56: Medicine | G56: Health Sciences | H56: V | I56: Crisis-driven (COVID) | J56: Keep | K56: Review | L56: 33151 | M56: =VLOOKUP(A56,'Matching with Cordis'!A$2:D$3447, 4, FALSE) -> 9 | N56: 4.357 | O56: 4 | P56: =AVERAGE(Q56:V56) -> 1.8623333 | Q56: 0.238 | R56: 0.138 | S56: 1.984 | T56: 3.851 | U56: 4.357 | V56: 0.606 | W56: 2020-2023
A57: https://openalex.org/T10275 | B57: =RIGHT(A57, LEN(A57) - FIND("/T", A57)) -> T10275 | D57: 2D Materials and Applications | F57: Materials Science | G57: Physical Sciences | H57: S | I57: Core S&T | J57: Keep | K57: Keep | L57: 48791 | M57: =VLOOKUP(A57,'Matching with Cordis'!A$2:D$3447, 4, FALSE) -> 129 | N57: 3.89 | O57: 6 | P57: =AVERAGE(Q57:V57) -> 1.8361667 | Q57: 0.478 | R57: 2.642 | S57: 3.89 | T57: 2.237 | U57: 1.037 | V57: 0.733 | W57: 2012-2015
A58: https://openalex.org/T13014 | B58: =RIGHT(A58, LEN(A58) - FIND("/T", A58)) -> T13014 | C58: =CONCAT(B58, ",") -> T13014, | D58: Peace and Human Rights Education | E58: =CONCATENATE(B58," ",D58,",") -> T13014 Peace and Human Rights Education, | F58: Social Sciences | G58: Social Sciences | H58: E | I58: Education & pedagogy | J58: Filter out | K58: Filter | L58: 5590 | M58: =VLOOKUP(A58,'Matching with Cordis'!A$2:D$3447, 4, FALSE) -> 11 | N58: 1.201 | O58: 4 | P58: =AVERAGE(Q58:V58) -> 0.425 | Q58: 1.201 | R58: 0.39 | S58: 0.459 | T58: 0.341 | U58: 0.029 | V58: 0.13 | W58: 2004-2007
A59: https://openalex.org/T12283 | B59: =RIGHT(A59, LEN(A59) - FIND("/T", A59)) -> T12283 | C59: =CONCAT(B59, ",") -> T12283, | D59: Latin American history and culture | E59: =CONCATENATE(B59," ",D59,",") -> T12283 Latin American history and culture, | F59: Arts and Humanities | G59: Social Sciences | H59: H | I59: Humanities & culture | J59: Filter out | K59: Filter | L59: 36510 | M59: =VLOOKUP(A59,'Matching with Cordis'!A$2:D$3447, 4, FALSE) -> 11 | N59: -0.262 | O59: 0 | P59: =AVERAGE(Q59:V59) -> -0.44566667 | Q59: -0.489 | R59: -0.462 | S59: -0.287 | T59: -0.478 | U59: -0.696 | V59: -0.262 | W59: 2024-2025
A60: https://openalex.org/T11070 | B60: =RIGHT(A60, LEN(A60) - FIND("/T", A60)) -> T11070 | C60: =CONCAT(B60, ",") -> T11070, | D60: Soviet and Russian History | E60: =CONCATENATE(B60," ",D60,",") -> T11070 Soviet and Russian History, | F60: Social Sciences | G60: Social Sciences | H60: K | I60: Country/region-specific | J60: Filter out | K60: Filter | L60: 29244 | M60: =VLOOKUP(A60,'Matching with Cordis'!A$2:D$3447, 4, FALSE) -> 11 | N60: -0.042 | O60: 0 | P60: =AVERAGE(Q60:V60) -> -0.60183333 | Q60: -1.177 | R60: -0.756 | S60: -0.732 | T60: -0.374 | U60: -0.53 | V60: -0.042 | W60: 2024-2025
A61: https://openalex.org/T14312 | B61: =RIGHT(A61, LEN(A61) - FIND("/T", A61)) -> T14312 | C61: =CONCAT(B61, ",") -> T14312, | D61: Historical Studies in Central America | E61: =CONCATENATE(B61," ",D61,",") -> T14312 Historical Studies in Central America, | F61: Arts and Humanities | G61: Social Sciences | H61: H | I61: Humanities & culture | J61: Filter out | K61: Filter | L61: 2533 | M61: =VLOOKUP(A61,'Matching with Cordis'!A$2:D$3447, 4, FALSE) -> 11 | N61: -0.004 | O61: 0 | P61: =AVERAGE(Q61:V61) -> -0.67366667 | Q61: -0.836 | R61: -0.768 | S61: -0.631 | T61: -0.688 | U61: -1.115 | V61: -0.004 | W61: 2024-2025
A62: https://openalex.org/T10883 | B62: =RIGHT(A62, LEN(A62) - FIND("/T", A62)) -> T10883 | D62: Ethics and Social Impacts of AI | F62: Social Sciences | G62: Social Sciences | H62: T | I62: Applied S&T | J62: Keep | K62: Keep | L62: 27022 | M62: =VLOOKUP(A62,'Matching with Cordis'!A$2:D$3447, 4, FALSE) -> 49 | N62: 2.916 | O62: 6 | P62: =AVERAGE(Q62:V62) -> 1.8101667 | Q62: 1.38 | R62: 1.04 | S62: 1.504 | T62: 2.916 | U62: 2.152 | V62: 1.869 | W62: 2016-2019
A63: https://openalex.org/T11690 | B63: =RIGHT(A63, LEN(A63) - FIND("/T", A63)) -> T11690 | D63: Advanced battery technologies research | F63: Engineering | G63: Physical Sciences | H63: S | I63: Core S&T | J63: Keep | K63: Keep | L63: 30965 | M63: =VLOOKUP(A63,'Matching with Cordis'!A$2:D$3447, 4, FALSE) -> 45 | N63: 2.49 | O63: 6 | P63: =AVERAGE(Q63:V63) -> 1.81 | Q63: 1.683 | R63: 2.181 | S63: 2.49 | T63: 2.11 | U63: 1.558 | V63: 0.838 | W63: 2012-2015
A64: https://openalex.org/T13499 | B64: =RIGHT(A64, LEN(A64) - FIND("/T", A64)) -> T13499 | C64: =CONCAT(B64, ",") -> T13499, | D64: Economic Systems and Logistics Management | E64: =CONCATENATE(B64," ",D64,",") -> T13499 Economic Systems and Logistics Management, | F64: Economics, Econometrics and Finance | G64: Social Sciences | H64: P | I64: Social science & policy | J64: Filter out | K64: Review | L64: 7249 | M64: =VLOOKUP(A64,'Matching with Cordis'!A$2:D$3447, 4, FALSE) -> 10 | N64: 1.687 | O64: 5 | P64: =AVERAGE(Q64:V64) -> 0.74483333 | Q64: -0.758 | R64: 1.203 | S64: 1.687 | T64: 0.937 | U64: 0.97 | V64: 0.43 | W64: 2012-2015
A65: https://openalex.org/T13434 | B65: =RIGHT(A65, LEN(A65) - FIND("/T", A65)) -> T13434 | C65: =CONCAT(B65, ",") -> T13434, | D65: Cancer Research and Treatment | E65: =CONCATENATE(B65," ",D65,",") -> T13434 Cancer Research and Treatment, | F65: Medicine | G65: Health Sciences | H65: B | I65: Biomedical research | J65: Filter out | K65: Keep | L65: 4869 | M65: =VLOOKUP(A65,'Matching with Cordis'!A$2:D$3447, 4, FALSE) -> 10 | N65: 1.288 | O65: 6 | P65: =AVERAGE(Q65:V65) -> 0.72133333 | Q65: 0.78 | R65: 0.532 | S65: 0.548 | T65: 1.288 | U65: 0.312 | V65: 0.868 | W65: 2016-2019
A66: https://openalex.org/T13063 | B66: =RIGHT(A66, LEN(A66) - FIND("/T", A66)) -> T13063 | C66: =CONCAT(B66, ",") -> T13063, | D66: Education and experiences of immigrants and refugees | E66: =CONCATENATE(B66," ",D66,",") -> T13063 Education and experiences of immigrants and refugees, | F66: Social Sciences | G66: Social Sciences | H66: E | I66: Education & pedagogy | J66: Filter out | K66: Filter | L66: 11322 | M66: =VLOOKUP(A66,'Matching with Cordis'!A$2:D$3447, 4, FALSE) -> 10 | N66: 1.265 | O66: 5 | P66: =AVERAGE(Q66:V66) -> 0.63466667 | Q66: 0.89 | R66: 0.897 | S66: 0.544 | T66: 1.265 | U66: 0.258 | V66: -0.046 | W66: 2016-2019
A67: https://openalex.org/T13749 | B67: =RIGHT(A67, LEN(A67) - FIND("/T", A67)) -> T13749 | C67: =CONCAT(B67, ",") -> T13749, | D67: Hungarian Social, Economic and Educational Studies | E67: =CONCATENATE(B67," ",D67,",") -> T13749 Hungarian Social, Economic and Educational Studies, | F67: Social Sciences | G67: Social Sciences | H67: K | I67: Country/region-specific | J67: Filter out | K67: Filter | L67: 80960 | M67: =VLOOKUP(A67,'Matching with Cordis'!A$2:D$3447, 4, FALSE) -> 10 | N67: 1.017 | O67: 4 | P67: =AVERAGE(Q67:V67) -> 0.50266667 | Q67: 0.13 | R67: 0.381 | S67: 0.597 | T67: 1.017 | U67: 0.696 | V67: 0.195 | W67: 2016-2019
A68: https://openalex.org/T13019 | B68: =RIGHT(A68, LEN(A68) - FIND("/T", A68)) -> T13019 | C68: =CONCAT(B68, ",") -> T13019, | D68: African Studies and Geopolitics | E68: =CONCATENATE(B68," ",D68,",") -> T13019 African Studies and Geopolitics, | F68: Social Sciences | G68: Social Sciences | H68: P | I68: Social science & policy | J68: Filter out | K68: Review | L68: 20155 | M68: =VLOOKUP(A68,'Matching with Cordis'!A$2:D$3447, 4, FALSE) -> 10 | N68: -0.102 | O68: 0 | P68: =AVERAGE(Q68:V68) -> -0.217 | Q68: -0.309 | R68: -0.179 | S68: -0.102 | T68: -0.326 | U68: -0.262 | V68: -0.124 | W68: 2012-2015
A69: https://openalex.org/T10763 | B69: =RIGHT(A69, LEN(A69) - FIND("/T", A69)) -> T10763 | D69: Digital Transformation in Industry | F69: Engineering | G69: Physical Sciences | H69: T | I69: Applied S&T | J69: Keep | K69: Keep | L69: 46964 | M69: =VLOOKUP(A69,'Matching with Cordis'!A$2:D$3447, 4, FALSE) -> 255 | N69: 3.517 | O69: 5 | P69: =AVERAGE(Q69:V69) -> 1.7843333 | Q69: -0.127 | R69: 1.047 | S69: 2.522 | T69: 3.517 | U69: 2.299 | V69: 1.448 | W69: 2016-2019
A70: https://openalex.org/T13993 | B70: =RIGHT(A70, LEN(A70) - FIND("/T", A70)) -> T13993 | C70: =CONCAT(B70, ",") -> T13993, | D70: Historical Geopolitical and Social Dynamics | E70: =CONCATENATE(B70," ",D70,",") -> T13993 Historical Geopolitical and Social Dynamics, | F70: Social Sciences | G70: Social Sciences | H70: K | I70: Country/region-specific | J70: Filter out | K70: Filter | L70: 46975 | M70: =VLOOKUP(A70,'Matching with Cordis'!A$2:D$3447, 4, FALSE) -> 10 | N70: 0.132 | O70: 0 | P70: =AVERAGE(Q70:V70) -> -0.265 | Q70: -0.655 | R70: -0.309 | S70: -0.258 | T70: -0.272 | U70: -0.228 | V70: 0.132 | W70: 2024-2025
A71: https://openalex.org/T12702 | B71: =RIGHT(A71, LEN(A71) - FIND("/T", A71)) -> T12702 | D71: Brain Tumor Detection and Classification | F71: Neuroscience | G71: Life Sciences | H71: B | I71: Biomedical research | J71: Keep | K71: Keep | L71: 31770 | M71: =VLOOKUP(A71,'Matching with Cordis'!A$2:D$3447, 4, FALSE) -> 4 | N71: 2.49 | O71: 6 | P71: =AVERAGE(Q71:V71) -> 1.7768333 | Q71: 1.206 | R71: 1.355 | S71: 1.591 | T71: 2.49 | U71: 2.081 | V71: 1.938 | W71: 2016-2019
A72: https://openalex.org/T14005 | B72: =RIGHT(A72, LEN(A72) - FIND("/T", A72)) -> T14005 | C72: =CONCAT(B72, ",") -> T14005, | D72: Eastern European Communism and Reforms | E72: =CONCATENATE(B72," ",D72,",") -> T14005 Eastern European Communism and Reforms, | F72: Social Sciences | G72: Social Sciences | H72: P | I72: Social science & policy | J72: Filter out | K72: Review | L72: 58715 | M72: =VLOOKUP(A72,'Matching with Cordis'!A$2:D$3447, 4, FALSE) -> 10 | N72: -0.073 | O72: 0 | P72: =AVERAGE(Q72:V72) -> -0.357 | Q72: -0.844 | R72: -0.545 | S72: -0.439 | T72: -0.083 | U72: -0.158 | V72: -0.073 | W72: 2024-2025
A73: https://openalex.org/T10273 | B73: =RIGHT(A73, LEN(A73) - FIND("/T", A73)) -> T10273 | D73: IoT and Edge/Fog Computing | F73: Computer Science | G73: Physical Sciences | H73: S | I73: Core S&T | J73: Keep | K73: Keep | L73: 65929 | M73: =VLOOKUP(A73,'Matching with Cordis'!A$2:D$3447, 4, FALSE) -> 124 | N73: 2.626 | O73: 6 | P73: =AVERAGE(Q73:V73) -> 1.7648333 | Q73: 1.441 | R73: 2.626 | S73: 2.603 | T73: 2.235 | U73: 1.274 | V73: 0.41 | W73: 2008-2011
A74: https://openalex.org/T13000 | B74: =RIGHT(A74, LEN(A74) - FIND("/T", A74)) -> T13000 | C74: =CONCAT(B74, ",") -> T13000, | D74: World Systems and Global Transformations | E74: =CONCATENATE(B74," ",D74,",") -> T13000 World Systems and Global Transformations, | F74: Social Sciences | G74: Social Sciences | H74: X | I74: Catch-all / vague | J74: Filter out | K74: Filter | L74: 7835 | M74: =VLOOKUP(A74,'Matching with Cordis'!A$2:D$3447, 4, FALSE) -> 10 | N74: 1.377 | O74: 1 | P74: =AVERAGE(Q74:V74) -> -0.71566667 | Q74: -1.528 | R74: -1.497 | S74: -0.679 | T74: -1.143 | U74: -0.824 | V74: 1.377 | W74: 2024-2025
A75: https://openalex.org/T14443 | B75: =RIGHT(A75, LEN(A75) - FIND("/T", A75)) -> T14443 | C75: =CONCAT(B75, ",") -> T14443, | D75: COVID-19, Geopolitics, Technology, Migration | E75: =CONCATENATE(B75," ",D75,",") -> T14443 COVID-19, Geopolitics, Technology, Migration, | F75: Social Sciences | G75: Social Sciences | H75: V | I75: Crisis-driven (COVID) | J75: Filter out | K75: Review | L75: 317 | M75: =VLOOKUP(A75,'Matching with Cordis'!A$2:D$3447, 4, FALSE) -> 9 | N75: 4.03 | O75: 4 | P75: =AVERAGE(Q75:V75) -> 1.781 | Q75: -0.35 | R75: 0.968 | S75: 2.181 | T75: 4.03 | U75: 3.898 | V75: -0.041 | W75: 2016-2019
A76: https://openalex.org/T12921 | B76: =RIGHT(A76, LEN(A76) - FIND("/T", A76)) -> T12921 | C76: =CONCAT(B76, ",") -> T12921, | D76: European Criminal Justice and Data Protection | E76: =CONCATENATE(B76," ",D76,",") -> T12921 European Criminal Justice and Data Protection, | F76: Social Sciences | G76: Social Sciences | H76: P | I76: Social science & policy | J76: Filter out | K76: Review | L76: 63169 | M76: =VLOOKUP(A76,'Matching with Cordis'!A$2:D$3447, 4, FALSE) -> 9 | N76: 0.383 | O76: 3 | P76: =AVERAGE(Q76:V76) -> 0.17516667 | Q76: 0.383 | R76: 0.36 | S76: 0.261 | T76: 0.224 | U76: -0.204 | V76: 0.027 | W76: 2004-2007
A77: https://openalex.org/T13041 | B77: =RIGHT(A77, LEN(A77) - FIND("/T", A77)) -> T13041 | C77: =CONCAT(B77, ",") -> T13041, | D77: Contemporary Social and Economic Issues | E77: =CONCATENATE(B77," ",D77,",") -> T13041 Contemporary Social and Economic Issues, | F77: Social Sciences | G77: Social Sciences | H77: P | I77: Social science & policy | J77: Filter out | K77: Review | L77: 809 | M77: =VLOOKUP(A77,'Matching with Cordis'!A$2:D$3447, 4, FALSE) -> 9 | N77: 0.904 | O77: 2 | P77: =AVERAGE(Q77:V77) -> 0.054 | Q77: -0.116 | R77: 0.904 | S77: 0.647 | T77: -0.405 | U77: -0.616 | V77: -0.09 | W77: 2008-2011
A78: https://openalex.org/T11711 | B78: =RIGHT(A78, LEN(A78) - FIND("/T", A78)) -> T11711 | D78: COVID-19 Pandemic Impacts | F78: Economics, Econometrics and Finance | G78: Social Sciences | H78: V | I78: Crisis-driven (COVID) | J78: Keep | K78: Review | L78: 59889 | M78: =VLOOKUP(A78,'Matching with Cordis'!A$2:D$3447, 4, FALSE) -> 1 | N78: 6.371 | O78: 5 | P78: =AVERAGE(Q78:V78) -> 1.7271667 | Q78: 2.097 | R78: 0.292 | S78: 0.852 | T78: 1.459 | U78: 6.371 | V78: -0.708 | W78: 2020-2023
A79: https://openalex.org/T14260 | B79: =RIGHT(A79, LEN(A79) - FIND("/T", A79)) -> T14260 | D79: Impact of AI and Big Data on Business and Society | F79: Decision Sciences | G79: Social Sciences | H79: T | I79: Applied S&T | J79: Keep | K79: Keep | L79: 17971 | M79: =VLOOKUP(A79,'Matching with Cordis'!A$2:D$3447, 4, FALSE) -> 15 | N79: 2.712 | O79: 6 | P79: =AVERAGE(Q79:V79) -> 1.7228333 | Q79: 1.295 | R79: 0.383 | S79: 1.113 | T79: 2.43 | U79: 2.404 | V79: 2.712 | W79: 2024-2025
A80: https://openalex.org/T11307 | B80: =RIGHT(A80, LEN(A80) - FIND("/T", A80)) -> T11307 | D80: Domain Adaptation and Few-Shot Learning | F80: Computer Science | G80: Physical Sciences | H80: S | I80: Core S&T | J80: Keep | K80: Keep | L80: 19145 | M80: =VLOOKUP(A80,'Matching with Cordis'!A$2:D$3447, 4, FALSE) -> 5 | N80: 2.609 | O80: 5 | P80: =AVERAGE(Q80:V80) -> 1.712 | Q80: 1.656 | R80: 2.499 | S80: 2.222 | T80: 2.609 | U80: 1.612 | V80: -0.326 | W80: 2016-2019
A81: https://openalex.org/T11479 | B81: =RIGHT(A81, LEN(A81) - FIND("/T", A81)) -> T11479 | D81: Smart Cities and Technologies | F81: Engineering | G81: Physical Sciences | H81: T | I81: Applied S&T | J81: Keep | K81: Keep | L81: 26816 | M81: =VLOOKUP(A81,'Matching with Cordis'!A$2:D$3447, 4, FALSE) -> 109 | N81: 2.842 | O81: 6 | P81: =AVERAGE(Q81:V81) -> 1.7116667 | Q81: 0.436 | R81: 2.358 | S81: 2.842 | T81: 2.109 | U81: 1.503 | V81: 1.022 | W81: 2012-2015
A82: https://openalex.org/T12972 | B82: =RIGHT(A82, LEN(A82) - FIND("/T", A82)) -> T12972 | C82: =CONCAT(B82, ",") -> T12972, | D82: German Colonialism and Identity Studies | E82: =CONCATENATE(B82," ",D82,",") -> T12972 German Colonialism and Identity Studies, | F82: Arts and Humanities | G82: Social Sciences | H82: K | I82: Country/region-specific | J82: Filter out | K82: Filter | L82: 7761 | M82: =VLOOKUP(A82,'Matching with Cordis'!A$2:D$3447, 4, FALSE) -> 9 | N82: -0.026 | O82: 0 | P82: =AVERAGE(Q82:V82) -> -0.19083333 | Q82: -0.352 | R82: -0.078 | S82: -0.026 | T82: -0.115 | U82: -0.083 | V82: -0.491 | W82: 2012-2015
A83: https://openalex.org/T12454 | B83: =RIGHT(A83, LEN(A83) - FIND("/T", A83)) -> T12454 | C83: =CONCAT(B83, ",") -> T12454, | D83: European Political History Analysis | E83: =CONCATENATE(B83," ",D83,",") -> T12454 European Political History Analysis, | F83: Arts and Humanities | G83: Social Sciences | H83: H | I83: Humanities & culture | J83: Filter out | K83: Filter | L83: 60534 | M83: =VLOOKUP(A83,'Matching with Cordis'!A$2:D$3447, 4, FALSE) -> 9 | N83: 0.289 | O83: 1 | P83: =AVERAGE(Q83:V83) -> -0.272 | Q83: -0.7 | R83: -0.254 | S83: -0.27 | T83: -0.25 | U83: -0.447 | V83: 0.289 | W83: 2024-2025
A84: https://openalex.org/T12079 | B84: =RIGHT(A84, LEN(A84) - FIND("/T", A84)) -> T12079 | D84: IoT Networks and Protocols | F84: Engineering | G84: Physical Sciences | H84: S | I84: Core S&T | J84: Keep | K84: Keep | L84: 11581 | M84: =VLOOKUP(A84,'Matching with Cordis'!A$2:D$3447, 4, FALSE) -> 20 | N84: 3.915 | O84: 4 | P84: =AVERAGE(Q84:V84) -> 1.7061667 | Q84: -1.517 | R84: 2.17 | S84: 3.915 | T84: 3.749 | U84: 1.746 | V84: 0.174 | W84: 2012-2015
A85: https://openalex.org/T14047 | B85: =RIGHT(A85, LEN(A85) - FIND("/T", A85)) -> T14047 | C85: =CONCAT(B85, ",") -> T14047, | D85: Marine and environmental studies | E85: =CONCATENATE(B85," ",D85,",") -> T14047 Marine and environmental studies, | F85: Earth and Planetary Sciences | G85: Physical Sciences | H85: S | I85: Core S&T | J85: Filter out | K85: Keep | L85: 67380 | M85: =VLOOKUP(A85,'Matching with Cordis'!A$2:D$3447, 4, FALSE) -> 9 | N85: 0.042 | O85: 0 | P85: =AVERAGE(Q85:V85) -> -0.35133333 | Q85: -0.626 | R85: -0.437 | S85: -0.434 | T85: -0.235 | U85: -0.418 | V85: 0.042 | W85: 2024-2025
A86: https://openalex.org/T10773 | B86: =RIGHT(A86, LEN(A86) - FIND("/T", A86)) -> T10773 | D86: Extracellular vesicles in disease | F86: Biochemistry, Genetics and Molecular Biology | G86: Life Sciences | H86: B | I86: Biomedical research | J86: Keep | K86: Keep | L86: 45584 | M86: =VLOOKUP(A86,'Matching with Cordis'!A$2:D$3447, 4, FALSE) -> 73 | N86: 2.299 | O86: 6 | P86: =AVERAGE(Q86:V86) -> 1.698 | Q86: 1.938 | R86: 2.299 | S86: 2.134 | T86: 1.8 | U86: 1.293 | V86: 0.724 | W86: 2008-2011
A87: https://openalex.org/T13081 | B87: =RIGHT(A87, LEN(A87) - FIND("/T", A87)) -> T13081 | C87: =CONCAT(B87, ",") -> T13081, | D87: Digital Education and Society | E87: =CONCATENATE(B87," ",D87,",") -> T13081 Digital Education and Society, | F87: Computer Science | G87: Physical Sciences | H87: E | I87: Education & pedagogy | J87: Filter out | K87: Filter | L87: 2657 | M87: =VLOOKUP(A87,'Matching with Cordis'!A$2:D$3447, 4, FALSE) -> 8 | N87: 2.212 | O87: 6 | P87: =AVERAGE(Q87:V87) -> 1.3676667 | Q87: 1.209 | R87: 1.78 | S87: 0.357 | T87: 2.183 | U87: 2.212 | V87: 0.465 | W87: 2020-2023
A88: https://openalex.org/T11754 | B88: =RIGHT(A88, LEN(A88) - FIND("/T", A88)) -> T11754 | D88: SARS-CoV-2 detection and testing | F88: Medicine | G88: Health Sciences | H88: V | I88: Crisis-driven (COVID) | J88: Keep | K88: Review | L88: 14058 | M88: =VLOOKUP(A88,'Matching with Cordis'!A$2:D$3447, 4, FALSE) -> 11 | N88: 5.077 | O88: 5 | P88: =AVERAGE(Q88:V88) -> 1.6918333 | Q88: 1.861 | R88: 0.869 | S88: 1.737 | T88: 1.301 | U88: 5.077 | V88: -0.694 | W88: 2020-2023
A89: https://openalex.org/T10664 | B89: =RIGHT(A89, LEN(A89) - FIND("/T", A89)) -> T10664 | D89: Sentiment Analysis and Opinion Mining | F89: Computer Science | G89: Physical Sciences | H89: S | I89: Core S&T | J89: Keep | K89: Keep | L89: 38941 | M89: =VLOOKUP(A89,'Matching with Cordis'!A$2:D$3447, 4, FALSE) -> 14 | N89: 3.589 | O89: 5 | P89: =AVERAGE(Q89:V89) -> 1.6743333 | Q89: 3.589 | R89: 2.314 | S89: 1.665 | T89: 1.315 | U89: 0.93 | V89: 0.233 | W89: 2004-2007
A90: https://openalex.org/T13514 | B90: =RIGHT(A90, LEN(A90) - FIND("/T", A90)) -> T13514 | C90: =CONCAT(B90, ",") -> T13514, | D90: Experience-Based Knowledge Management | E90: =CONCATENATE(B90," ",D90,",") -> T13514 Experience-Based Knowledge Management, | F90: Computer Science | G90: Physical Sciences | H90: S | I90: Core S&T | J90: Filter out | K90: Keep | L90: 933 | M90: =VLOOKUP(A90,'Matching with Cordis'!A$2:D$3447, 4, FALSE) -> 8 | N90: 1.804 | O90: 4 | P90: =AVERAGE(Q90:V90) -> 0.81933333 | Q90: 1.289 | R90: 1.616 | S90: 1.804 | T90: 0.422 | U90: -0.367 | V90: 0.152 | W90: 2012-2015
A91: https://openalex.org/T12320 | B91: =RIGHT(A91, LEN(A91) - FIND("/T", A91)) -> T12320 | C91: =CONCAT(B91, ",") -> T12320, | D91: Feminist Epistemology and Gender Studies | E91: =CONCATENATE(B91," ",D91,",") -> T12320 Feminist Epistemology and Gender Studies, | F91: Social Sciences | G91: Social Sciences | H91: P | I91: Social science & policy | J91: Filter out | K91: Review | L91: 3423 | M91: =VLOOKUP(A91,'Matching with Cordis'!A$2:D$3447, 4, FALSE) -> 8 | N91: 0.448 | O91: 3 | P91: =AVERAGE(Q91:V91) -> 0.098333333 | Q91: -0.061 | R91: -0.317 | S91: 0.448 | T91: 0.374 | U91: 0.418 | V91: -0.272 | W91: 2012-2015
A92: https://openalex.org/T13103 | B92: =RIGHT(A92, LEN(A92) - FIND("/T", A92)) -> T13103 | C92: =CONCAT(B92, ",") -> T13103, | D92: Middle East Politics and Society | E92: =CONCATENATE(B92," ",D92,",") -> T13103 Middle East Politics and Society, | F92: Social Sciences | G92: Social Sciences | H92: K | I92: Country/region-specific | J92: Filter out | K92: Filter | L92: 28762 | M92: =VLOOKUP(A92,'Matching with Cordis'!A$2:D$3447, 4, FALSE) -> 8 | N92: 0.387 | O92: 2 | P92: =AVERAGE(Q92:V92) -> 0.015833333 | Q92: 0.071 | R92: -0.09 | S92: 0.322 | T92: -0.203 | U92: -0.392 | V92: 0.387 | W92: 2024-2025
A93: https://openalex.org/T12585 | B93: =RIGHT(A93, LEN(A93) - FIND("/T", A93)) -> T12585 | C93: =CONCAT(B93, ",") -> T12585, | D93: North African History and Literature | E93: =CONCATENATE(B93," ",D93,",") -> T12585 North African History and Literature, | F93: Arts and Humanities | G93: Social Sciences | H93: K | I93: Country/region-specific | J93: Filter out | K93: Filter | L93: 7990 | M93: =VLOOKUP(A93,'Matching with Cordis'!A$2:D$3447, 4, FALSE) -> 8 | N93: 0.155 | O93: 0 | P93: =AVERAGE(Q93:V93) -> -0.24566667 | Q93: -0.245 | R93: -0.089 | S93: 0.155 | T93: -0.214 | U93: -0.384 | V93: -0.697 | W93: 2012-2015
A94: https://openalex.org/T10657 | B94: =RIGHT(A94, LEN(A94) - FIND("/T", A94)) -> T10657 | D94: Topological Materials and Phenomena | F94: Physics and Astronomy | G94: Physical Sciences | H94: S | I94: Core S&T | J94: Keep | K94: Keep | L94: 36797 | M94: =VLOOKUP(A94,'Matching with Cordis'!A$2:D$3447, 4, FALSE) -> 152 | N94: 2.721 | O94: 6 | P94: =AVERAGE(Q94:V94) -> 1.6538333 | Q94: 2.48 | R94: 2.721 | S94: 2.165 | T94: 1.31 | U94: 0.747 | V94: 0.5 | W94: 2008-2011
A95: https://openalex.org/T12302 | B95: =RIGHT(A95, LEN(A95) - FIND("/T", A95)) -> T12302 | D95: Advanced Nanomaterials in Catalysis | F95: Materials Science | G95: Physical Sciences | H95: S | I95: Core S&T | J95: Keep | K95: Keep | L95: 24301 | M95: =VLOOKUP(A95,'Matching with Cordis'!A$2:D$3447, 4, FALSE) -> 8 | N95: 2.118 | O95: 6 | P95: =AVERAGE(Q95:V95) -> 1.6531667 | Q95: 1.861 | R95: 2.118 | S95: 1.857 | T95: 1.498 | U95: 1.316 | V95: 1.269 | W95: 2008-2011
A96: https://openalex.org/T10893 | B96: =RIGHT(A96, LEN(A96) - FIND("/T", A96)) -> T10893 | C96: =CONCAT(B96, ",") -> T10893, | D96: Chinese history and philosophy | E96: =CONCATENATE(B96," ",D96,",") -> T10893 Chinese history and philosophy, | F96: Social Sciences | G96: Social Sciences | H96: K | I96: Country/region-specific | J96: Filter out | K96: Filter | L96: 216371 | M96: =VLOOKUP(A96,'Matching with Cordis'!A$2:D$3447, 4, FALSE) -> 8 | N96: 0.136 | O96: 0 | P96: =AVERAGE(Q96:V96) -> -0.31183333 | Q96: -0.251 | R96: -0.332 | S96: -0.725 | T96: -0.492 | U96: -0.207 | V96: 0.136 | W96: 2024-2025
A97: https://openalex.org/T14431 | B97: =RIGHT(A97, LEN(A97) - FIND("/T", A97)) -> T14431 | C97: =CONCAT(B97, ",") -> T14431, | D97: Diverse Research and Applications | E97: =CONCATENATE(B97," ",D97,",") -> T14431 Diverse Research and Applications, | F97: Computer Science | G97: Physical Sciences | H97: X | I97: Catch-all / vague | J97: Filter out | K97: Filter | L97: 2786 | M97: =VLOOKUP(A97,'Matching with Cordis'!A$2:D$3447, 4, FALSE) -> 8 | N97: 0.167 | O97: 0 | P97: =AVERAGE(Q97:V97) -> -0.44833333 | Q97: -0.394 | R97: -0.231 | S97: -0.45 | T97: -0.67 | U97: -1.112 | V97: 0.167 | W97: 2024-2025
A98: https://openalex.org/T10247 | B98: =RIGHT(A98, LEN(A98) - FIND("/T", A98)) -> T10247 | D98: Perovskite Materials and Applications | F98: Engineering | G98: Physical Sciences | H98: S | I98: Core S&T | J98: Keep | K98: Keep | L98: 80377 | M98: =VLOOKUP(A98,'Matching with Cordis'!A$2:D$3447, 4, FALSE) -> 112 | N98: 2.919 | O98: 6 | P98: =AVERAGE(Q98:V98) -> 1.6425 | Q98: 1.042 | R98: 1.493 | S98: 2.919 | T98: 2.223 | U98: 1.27 | V98: 0.908 | W98: 2012-2015
A99: https://openalex.org/T11396 | B99: =RIGHT(A99, LEN(A99) - FIND("/T", A99)) -> T11396 | C99: =CONCAT(B99, ",") -> T11396, | D99: Artificial Intelligence in Healthcare | E99: =CONCATENATE(B99," ",D99,",") -> T11396 Artificial Intelligence in Healthcare, | F99: Health Professions | G99: Health Sciences | H99: T | I99: Applied S&T | J99: Filter out | K99: Keep | L99: 48389 | M99: =VLOOKUP(A99,'Matching with Cordis'!A$2:D$3447, 4, FALSE) -> 7 | N99: 2.121 | O99: 5 | P99: =AVERAGE(Q99:V99) -> 1.4806667 | Q99: 2.033 | R99: 0.03 | S99: 1.637 | T99: 2.121 | U99: 1.715 | V99: 1.348 | W99: 2016-2019
A100: https://openalex.org/T14319 | B100: =RIGHT(A100, LEN(A100) - FIND("/T", A100)) -> T14319 | C100: =CONCAT(B100, ",") -> T14319, | D100: Currency Recognition and Detection | E100: =CONCATENATE(B100," ",D100,",") -> T14319 Currency Recognition and Detection, | F100: Computer Science | G100: Physical Sciences | H100: S | I100: Core S&T | J100: Filter out | K100: Keep | L100: 5642 | M100: =VLOOKUP(A100,'Matching with Cordis'!A$2:D$3447, 4, FALSE) -> 7 | N100: 2.325 | O100: 6 | P100: =AVERAGE(Q100:V100) -> 1.1751667 | Q100: 0.599 | R100: 0.306 | S100: 1.008 | T100: 2.325 | U100: 1.859 | V100: 0.954 | W100: 2016-2019
A101: https://openalex.org/T10768 | B101: =RIGHT(A101, LEN(A101) - FIND("/T", A101)) -> T10768 | D101: Electric Vehicles and Infrastructure | F101: Engineering | G101: Physical Sciences | H101: S | I101: Core S&T | J101: Keep | K101: Keep | L101: 49227 | M101: =VLOOKUP(A101,'Matching with Cordis'!A$2:D$3447, 4, FALSE) -> 94 | N101: 2.671 | O101: 6 | P101: =AVERAGE(Q101:V101) -> 1.6308333 | Q101: 0.863 | R101: 2.671 | S101: 2.222 | T101: 1.526 | U101: 1.557 | V101: 0.946 | W101: 2008-2011
A102: https://openalex.org/T10579 | B102: =RIGHT(A102, LEN(A102) - FIND("/T", A102)) -> T10579 | D102: Cognitive Radio Networks and Spectrum Sensing | F102: Computer Science | G102: Physical Sciences | H102: S | I102: Core S&T | J102: Keep | K102: Keep | L102: 28076 | M102: =VLOOKUP(A102,'Matching with Cordis'!A$2:D$3447, 4, FALSE) -> 27 | N102: 6.304 | O102: 3 | P102: =AVERAGE(Q102:V102) -> 1.6298333 | Q102: 6.304 | R102: 4.084 | S102: 0.646 | T102: -0.179 | U102: -0.455 | V102: -0.621 | W102: 2004-2007
A103: https://openalex.org/T13948 | B103: =RIGHT(A103, LEN(A103) - FIND("/T", A103)) -> T13948 | C103: =CONCAT(B103, ",") -> T13948, | D103: European Union Immigration and Asylum Policies | E103: =CONCATENATE(B103," ",D103,",") -> T13948 European Union Immigration and Asylum Policies, | F103: Social Sciences | G103: Social Sciences | H103: P | I103: Social science & policy | J103: Filter out | K103: Review | L103: 17399 | M103: =VLOOKUP(A103,'Matching with Cordis'!A$2:D$3447, 4, FALSE) -> 7 | N103: 1.41 | O103: 6 | P103: =AVERAGE(Q103:V103) -> 0.97833333 | Q103: 1.005 | R103: 0.633 | S103: 1.187 | T103: 1.41 | U103: 1.109 | V103: 0.526 | W103: 2016-2019
A104: https://openalex.org/T13669 | B104: =RIGHT(A104, LEN(A104) - FIND("/T", A104)) -> T13669 | C104: =CONCAT(B104, ",") -> T13669, | D104: China's Global Influence and Migration | E104: =CONCATENATE(B104," ",D104,",") -> T13669 China's Global Influence and Migration, | F104: Social Sciences | G104: Social Sciences | H104: K | I104: Country/region-specific | J104: Filter out | K104: Filter | L104: 7144 | M104: =VLOOKUP(A104,'Matching with Cordis'!A$2:D$3447, 4, FALSE) -> 7 | N104: 0.937 | O104: 4 | P104: =AVERAGE(Q104:V104) -> 0.43833333 | Q104: 0.937 | R104: 0.651 | S104: 0.586 | T104: 0.783 | U104: 0.241 | V104: -0.568 | W104: 2004-2007
A105: https://openalex.org/T11273 | B105: =RIGHT(A105, LEN(A105) - FIND("/T", A105)) -> T11273 | D105: Advanced Graph Neural Networks | F105: Computer Science | G105: Physical Sciences | H105: S | I105: Core S&T | J105: Keep | K105: Keep | L105: 16639 | M105: =VLOOKUP(A105,'Matching with Cordis'!A$2:D$3447, 4, FALSE) -> 5 | N105: 2.43 | O105: 6 | P105: =AVERAGE(Q105:V105) -> 1.6063333 | Q105: 2.43 | R105: 2.052 | S105: 1.471 | T105: 1.758 | U105: 1.446 | V105: 0.481 | W105: 2004-2007
A106: https://openalex.org/T10270 | B106: =RIGHT(A106, LEN(A106) - FIND("/T", A106)) -> T10270 | D106: Blockchain Technology Applications and Security | F106: Computer Science | G106: Physical Sciences | H106: S | I106: Core S&T | J106: Keep | K106: Keep | L106: 80970 | M106: =VLOOKUP(A106,'Matching with Cordis'!A$2:D$3447, 4, FALSE) -> 61 | N106: 3.103 | O106: 5 | P106: =AVERAGE(Q106:V106) -> 1.605 | Q106: 0.204 | R106: 1.561 | S106: 2.032 | T106: 3.103 | U106: 1.869 | V106: 0.861 | W106: 2016-2019
...

Sheet Sheet2
A1: Topic ID
A2: T13703
A3: T13436
A4: T13656
A5: T10289
A6: T14152
A7: T14347
A8: T14440
A9: T12981
A10: T14213
A11: T12959
A12: T14491
... A812: T13064

Sheet Monitoring progress
D2: =B2/B4 -> 0.1795837

Sheet Matching with Cordis
A1: topic_id | B1: topic_name | C1: domain_name | D1: n_projects | E1: avg_frontier
A2: https://openalex.org/T11524 | B2: Advanced Aircraft Design and Technologies | C2: Physical Sciences | D2: 294 | E2: 0.43663668
A3: https://openalex.org/T10763 | B3: Digital Transformation in Industry | C3: Physical Sciences | D3: 255 | E3: 2.793644
A4: https://openalex.org/T14147 | B4: Innovative Approaches in Technology and Social Development | C4: Social Sciences | D4: 241 | E4: 0.40904573
A5: https://openalex.org/T13726 | B5: International Science and Diplomacy | C5: Social Sciences | D5: 227 | E5: -0.012300117
A6: https://openalex.org/T11489 | B6: Air Traffic Management and Optimization | C6: Physical Sciences | D6: 217 | E6: 0.25006489
A7: https://openalex.org/T10119 | B7: Sustainability and Climate Change Governance | C7: Physical Sciences | D7: 216 | E7: 0.47987034
A8: https://openalex.org/T11185 | B8: Integrated Energy Systems Optimization | C8: Physical Sciences | D8: 210 | E8: 1.4605274
A9: https://openalex.org/T13240 | B9: Bioeconomy and Sustainability Development | C9: Life Sciences | D9: 210 | E9: 1.1053384
A10: https://openalex.org/T11190 | B10: 3D Printing in Biomedical Research | C10: Physical Sciences | D10: 205 | E10: 0.56487297
A11: https://openalex.org/T10184 | B11: Plant Molecular Biology Research | C11: Life Sciences | D11: 203 | E11: -0.2354159
A12: https://openalex.org/T10603 | B12: Smart Grid Energy Management | C12: Physical Sciences | D12: 198 | E12: 1.1817511
A13: https://openalex.org/T12414 | B13: Coastal and Marine Management | C13: Physical Sciences | D13: 193 | E13: 0.29116701
... A3448: https://openalex.org/T13370 | B3448: Diverse Scientific and Economic Studies | C3448: Social Sciences | D3448: 1 | E3448: -2.3684442

Sheet Taxonomy
A1: Code | B1: Category | C1: Count | D1: % of total | E1: Description | F1: Claude commentary
A2: S | B2: Core S&T | C2: 1484 | D2: 32.9 | E2: Hard science, engineering, computer science, mathematics, materials, physics, chemistry, energy. | F2: Core ACCORD scope.
A3: B | B3: Biomedical research | C3: 1050 | D3: 23.3 | E3: Molecular, cellular, genetic, pharmacological research. Disease mechanisms, drug development, -omics. | F3: Core ACCORD scope.
A4: T | B4: Applied S&T | C4: 297 | D4: 6.6 | E4: S&T methods applied to sectors: AI in healthcare, smart agriculture, digital transformation, computational social science. | F4: Core ACCORD scope.
A5: P | B5: Social science & policy | C5: 568 | D5: 12.6 | E5: Law, sociology, political science, economics (qualitative), migration, gender studies. May contain some policy-relevant R&I content. | F5: Case-by-case; some topics may have S&T relevance.
A6: Y | B6: Psychology & behavioural | C6: 118 | D6: 2.6 | E6: Therapy, psychometrics, cognitive/behavioural research. Some neuroscience overlap. | F6: Case-by-case; some topics may have S&T relevance.
A7: C | B7: Clinical & health practice | C7: 111 | D7: 2.5 | E7: Nursing, patient care, health services, occupational health, rehabilitation. Practice-oriented. | F7: Case-by-case; some topics may have S&T relevance.
A8: V | B8: Crisis-driven (COVID) | C8: 22 | D8: 0.5 | E8: Pandemic-specific topics. Genuine research but exogenous shock distorting temporal comparisons. | F8: Case-by-case; some topics may have S&T relevance.
A9: E | B9: Education & pedagogy | C9: 210 | D9: 4.7 | E9: Teaching methods, e-learning, curriculum, school systems, student outcomes. High publication volume growth but not S&T frontier. | F9: Persistent top-quartile noise; not S&T frontier.
A10: H | B10: Humanities & culture | C10: 238 | D10: 5.3 | E10: Literature, history, theology, philosophy, art, archaeology, cultural studies. Not S&T research. | F10: Persistent top-quartile noise; not S&T frontier.
A11: M | B11: Business & management | C11: 168 | D11: 3.7 | E11: Corporate governance, HR, marketing, supply chain, leadership. Not S&T research. | F11: Persistent top-quartile noise; not S&T frontier.
A12: X | B12: Catch-all / vague | C12: 101 | D12: 2.2 | E12: Generic OA categories with no coherent domain. Aggregation artefacts. | F12: Persistent top-quartile noise; not S&T frontier.
A13: K | B13: Country/region-specific | C13: 127 | D13: 2.8 | E13: National/regional society, politics, law, history, culture topics. Reflects country-level publication growth, not global S&T frontier. Applied consistently across ALL geographies. | F13: Persistent top-quartile noise; not S&T frontier.
A14: L | B14: Sports, tourism & leisure | C14: 22 | D14: 0.5 | E14: Sports science, tourism management, hospitality. Not S&T research. | F14: Persistent top-quartile noise; not S&T frontier.

Sheet topic_count_GBQ
A1: topic_id | B1: num_works | C1: Topic ID no url
A2: 10001 | B2: 150218 | C2: T10001
A3: 10002 | B3: 74259 | C3: T10002
A4: 10003 | B4: 70644 | C4: T10003
A5: 10004 | B5: 77972 | C5: T10004
A6: 10005 | B6: 62930 | C6: T10005
A7: 10006 | B7: 69257 | C7: T10006
A8: 10007 | B8: 85649 | C8: T10007
A9: 10008 | B9: 60498 | C9: T10008
A10: 10009 | B10: 74582 | C10: T10009
A11: 10010 | B11: 93414 | C11: T10010
A12: 10011 | B12: 18633 | C12: T10011
A13: 10012 | B13: 38194 | C13: T10012
... A4517: 14521 | B4517: 38368 | C4517: T14521
